{
    "modules": [
        {
            "id": "travel-expense-intelligent",
            "name": "差旅费智能识别",
            "version": "1.0.0",
            "description": "上传发票、支付记录、审批表等文件，自动识别提取关键信息并生成完整报销文档",
            "author": "AI Assistant",
            "icon": "📋",
            "category": "财务工具",
            "entry": "./modules/travel-expense-intelligent/travel-expense-intelligent.js",
            "enabled": true,
            "permissions": ["file-upload", "file-download"]
        }
    ],
    "version": "1.0.0",
    "description": "GitHub仓库模块配置，在此添加需要动态加载的模块名称"
}
